exiv/__init__.py
exiv/core.py
exiv-0.0.1.dist-info/licenses/LICENSE
exiv-0.0.1.dist-info/METADATA
exiv-0.0.1.dist-info/WHEEL
exiv-0.0.1.dist-info/top_level.txt
exiv-0.0.1.dist-info/RECORD
